MANIFEST.in
README.rst
setup.py
ordenley/__init__.py
ordenley/remove.py
ordenley.egg-info/PKG-INFO
ordenley.egg-info/SOURCES.txt
ordenley.egg-info/dependency_links.txt
ordenley.egg-info/entry_points.txt
ordenley.egg-info/requires.txt
ordenley.egg-info/top_level.txt
ordenley/controllers/__init__.py
ordenley/controllers/controller.py
ordenley/db/__init__.py
ordenley/db/db_manager.py
ordenley/models/Models.py
ordenley/models/__init__.py
ordenley/tests/__init__.py
ordenley/tests/controllers_test.py
ordenley/tests/db_test.py
ordenley/tests/models_test.py
ordenley/tests/run.py
ordenley/tests/views_test.py
ordenley/views/__init__.py
ordenley/views/client.py
ordenley/views/main.py
ordenley/views/interfaces/client_view.glade
ordenley/views/interfaces/main_view.glade