Metadata-Version: 1.1
Name: ordenley
Version: 0.2.1dev
Summary: Manager desktop app oriented to lawyers office
Home-page: http://github.com/tuxskar/ord-en-ley
Author: Oscar Ramirez
Author-email: tuxskar@gmail.com
License: GPLv3
Platform: UNKNOWN
Classifier: Development Status :: 3 - Alpha
Classifier: Intended Audience :: End Users/Desktop
Classifier: License :: OSI Approved :: GNU General Public License v3 (GPLv3)
Classifier: Environment :: X11 Applications :: GTK
Classifier: Operating System :: POSIX :: Linux
Classifier: Operating System :: Microsoft :: Windows
Classifier: Operating System :: MacOS
Classifier: Programming Language :: Python :: 2.7
